{
    "logs": [
        {
            "outputFile": "C:\\Users\\Dicky Adhadyanto\\AndroidStudioProjects\\IndoTrucker\\app\\build\\intermediates\\incremental\\mergeDebugResources\\merged.dir\\values\\values.xml",
            "map": [
                {
                    "source": "C:\\Users\\Dicky Adhadyanto\\.gradle\\caches\\transforms-2\\files-2.1\\5b48761f01c7c76a556c530a8a008e34\\res\\values\\values.xml",
                    "from": {
                        "startLines": "-1,-1,-1,-1,-1,-1,-1,-1,-1,-1,-1,-1,-1,-1,-1,-1,-1,-1,-1,-1,-1,-1,-1,-1,-1,-1,-1,-1,-1,-1,-1,-1,-1,-1,-1,-1,-1,-1,-1,-1,-1,-1,-1,-1,-1,-1,-1,-1,-1,-1,-1,-1,-1,-1,-1,-1,-1,-1,-1,-1,-1,-1,-1,-1,-1,-1,-1,-1,-1,-1,-1,-1,-1,-1,-1,-1,-1,-1,-1,-1,-1,-1,-1,-1,-1,-1,-1,-1,-1,-1,-1,-1,-1,-1,-1,-1,-1,-1,-1,-1,-1,-1,-1,-1,-1,-1,-1,-1,-1,-1,-1,-1,-1,-1,-1,-1,-1,-1,-1,-1,-1,-1,-1,-1,-1,-1,-1,-1,-1,-1,-1,-1,-1,-1,-1,-1,-1,-1,-1,-1,-1,-1,-1,-1,-1,-1,-1,-1,-1,-1,-1,-1,-1,-1,-1,-1,-1,-1,-1,-1,-1,-1,-1,-1,-1,-1,-1,-1,-1,-1,-1,-1,-1,-1,-1,-1,-1,-1,-1,-1,-1,-1,-1,-1,-1,-1,-1,-1,-1,-1,-1,-1,-1,-1,-1,-1,-1,-1,-1,-1,-1,-1,-1,-1,-1,-1,-1,-1,-1,-1,-1,-1,-1,-1,-1,-1,-1,-1,-1,-1,-1,-1,-1,-1,-1,-1,-1,-1,-1,-1,-1,-1,-1,-1,-1,-1,-1,-1,-1,-1,-1,-1,-1,-1,-1,-1,-1,-1,-1,-1,-1,-1,-1,-1,-1,-1,-1,-1,-1,-1,-1,-1,-1,-1,-1,-1,-1,-1,-1,-1,-1,-1,-1,-1,-1,-1,-1,-1,-1,-1,-1,-1,-1,-1,-1,-1,-1,-1,-1,-1,-1,-1,-1,-1,-1,-1,-1,-1,-1,-1,-1,-1,-1,-1,-1,-1,-1,-1,-1,-1,-1,-1,-1,-1,-1,-1,-1,-1,-1,-1,-1,-1,-1,-1,-1,-1,-1,-1,-1,-1,-1,-1,-1,-1,-1,-1,-1,-1,-1,-1,-1,-1,-1,-1,-1,-1,-1,-1,-1,-1,-1,-1,-1,-1,-1,-1,-1,-1,-1,-1,-1,-1,-1,-1,-1,-1,-1,-1,-1,-1,-1,-1,-1,-1,-1,-1,-1,-1,-1,-1,-1,-1,-1,-1,-1,-1,-1,-1,-1,-1,-1,-1,-1,-1,-1,-1,-1,-1,-1,-1,-1,-1,-1,-1,-1,-1,-1,-1,-1,-1,-1,-1,-1,-1,-1,-1,-1,-1,-1,-1,-1,-1,-1,-1,-1,-1,-1,-1,-1,-1,-1,-1,-1,-1,-1,-1,-1,-1,-1,-1,-1,-1,-1,-1,-1,-1,-1,-1,-1,-1,-1,-1,-1,-1,-1,-1,-1,-1,-1,-1,-1,-1,-1,-1,-1,-1,-1,-1,-1,-1,-1,-1,-1,-1,-1,-1,-1,-1,-1,-1,-1,-1,-1,-1,-1,-1,-1,-1,-1,-1,-1,-1,-1,-1,-1,-1,-1,-1,-1,-1,-1,-1,-1,-1,-1,-1,-1,-1,-1,-1,-1,-1,-1,-1,-1,-1,-1,-1,-1,-1,-1,-1,-1,-1,-1,-1,-1,-1,-1,-1",
                        "startColumns": "-1,-1,-1,-1,-1,-1,-1,-1,-1,-1,-1,-1,-1,-1,-1,-1,-1,-1,-1,-1,-1,-1,-1,-1,-1,-1,-1,-1,-1,-1,-1,-1,-1,-1,-1,-1,-1,-1,-1,-1,-1,-1,-1,-1,-1,-1,-1,-1,-1,-1,-1,-1,-1,-1,-1,-1,-1,-1,-1,-1,-1,-1,-1,-1,-1,-1,-1,-1,-1,-1,-1,-1,-1,-1,-1,-1,-1,-1,-1,-1,-1,-1,-1,-1,-1,-1,-1,-1,-1,-1,-1,-1,-1,-1,-1,-1,-1,-1,-1,-1,-1,-1,-1,-1,-1,-1,-1,-1,-1,-1,-1,-1,-1,-1,-1,-1,-1,-1,-1,-1,-1,-1,-1,-1,-1,-1,-1,-1,-1,-1,-1,-1,-1,-1,-1,-1,-1,-1,-1,-1,-1,-1,-1,-1,-1,-1,-1,-1,-1,-1,-1,-1,-1,-1,-1,-1,-1,-1,-1,-1,-1,-1,-1,-1,-1,-1,-1,-1,-1,-1,-1,-1,-1,-1,-1,-1,-1,-1,-1,-1,-1,-1,-1,-1,-1,-1,-1,-1,-1,-1,-1,-1,-1,-1,-1,-1,-1,-1,-1,-1,-1,-1,-1,-1,-1,-1,-1,-1,-1,-1,-1,-1,-1,-1,-1,-1,-1,-1,-1,-1,-1,-1,-1,-1,-1,-1,-1,-1,-1,-1,-1,-1,-1,-1,-1,-1,-1,-1,-1,-1,-1,-1,-1,-1,-1,-1,-1,-1,-1,-1,-1,-1,-1,-1,-1,-1,-1,-1,-1,-1,-1,-1,-1,-1,-1,-1,-1,-1,-1,-1,-1,-1,-1,-1,-1,-1,-1,-1,-1,-1,-1,-1,-1,-1,-1,-1,-1,-1,-1,-1,-1,-1,-1,-1,-1,-1,-1,-1,-1,-1,-1,-1,-1,-1,-1,-1,-1,-1,-1,-1,-1,-1,-1,-1,-1,-1,-1,-1,-1,-1,-1,-1,-1,-1,-1,-1,-1,-1,-1,-1,-1,-1,-1,-1,-1,-1,-1,-1,-1,-1,-1,-1,-1,-1,-1,-1,-1,-1,-1,-1,-1,-1,-1,-1,-1,-1,-1,-1,-1,-1,-1,-1,-1,-1,-1,-1,-1,-1,-1,-1,-1,-1,-1,-1,-1,-1,-1,-1,-1,-1,-1,-1,-1,-1,-1,-1,-1,-1,-1,-1,-1,-1,-1,-1,-1,-1,-1,-1,-1,-1,-1,-1,-1,-1,-1,-1,-1,-1,-1,-1,-1,-1,-1,-1,-1,-1,-1,-1,-1,-1,-1,-1,-1,-1,-1,-1,-1,-1,-1,-1,-1,-1,-1,-1,-1,-1,-1,-1,-1,-1,-1,-1,-1,-1,-1,-1,-1,-1,-1,-1,-1,-1,-1,-1,-1,-1,-1,-1,-1,-1,-1,-1,-1,-1,-1,-1,-1,-1,-1,-1,-1,-1,-1,-1,-1,-1,-1,-1,-1,-1,-1,-1,-1,-1,-1,-1,-1,-1,-1,-1,-1,-1,-1,-1,-1,-1,-1,-1,-1,-1,-1,-1,-1,-1,-1,-1,-1,-1,-1,-1,-1,-1,-1,-1,-1,-1,-1,-1,-1,-1,-1,-1,-1,-1,-1,-1,-1,-1,-1,-1",
                        "startOffsets": "-1,-1,-1,-1,-1,-1,-1,-1,-1,-1,-1,-1,-1,-1,-1,-1,-1,-1,-1,-1,-1,-1,-1,-1,-1,-1,-1,-1,-1,-1,-1,-1,-1,-1,-1,-1,-1,-1,-1,-1,-1,-1,-1,-1,-1,-1,-1,-1,-1,-1,-1,-1,-1,-1,-1,-1,-1,-1,-1,-1,-1,-1,-1,-1,-1,-1,-1,-1,-1,-1,-1,-1,-1,-1,-1,-1,-1,-1,-1,-1,-1,-1,-1,-1,-1,-1,-1,-1,-1,-1,-1,-1,-1,-1,-1,-1,-1,-1,-1,-1,-1,-1,-1,-1,-1,-1,-1,-1,-1,-1,-1,-1,-1,-1,-1,-1,-1,-1,-1,-1,-1,-1,-1,-1,-1,-1,-1,-1,-1,-1,-1,-1,-1,-1,-1,-1,-1,-1,-1,-1,-1,-1,-1,-1,-1,-1,-1,-1,-1,-1,-1,-1,-1,-1,-1,-1,-1,-1,-1,-1,-1,-1,-1,-1,-1,-1,-1,-1,-1,-1,-1,-1,-1,-1,-1,-1,-1,-1,-1,-1,-1,-1,-1,-1,-1,-1,-1,-1,-1,-1,-1,-1,-1,-1,-1,-1,-1,-1,-1,-1,-1,-1,-1,-1,-1,-1,-1,-1,-1,-1,-1,-1,-1,-1,-1,-1,-1,-1,-1,-1,-1,-1,-1,-1,-1,-1,-1,-1,-1,-1,-1,-1,-1,-1,-1,-1,-1,-1,-1,-1,-1,-1,-1,-1,-1,-1,-1,-1,-1,-1,-1,-1,-1,-1,-1,-1,-1,-1,-1,-1,-1,-1,-1,-1,-1,-1,-1,-1,-1,-1,-1,-1,-1,-1,-1,-1,-1,-1,-1,-1,-1,-1,-1,-1,-1,-1,-1,-1,-1,-1,-1,-1,-1,-1,-1,-1,-1,-1,-1,-1,-1,-1,-1,-1,-1,-1,-1,-1,-1,-1,-1,-1,-1,-1,-1,-1,-1,-1,-1,-1,-1,-1,-1,-1,-1,-1,-1,-1,-1,-1,-1,-1,-1,-1,-1,-1,-1,-1,-1,-1,-1,-1,-1,-1,-1,-1,-1,-1,-1,-1,-1,-1,-1,-1,-1,-1,-1,-1,-1,-1,-1,-1,-1,-1,-1,-1,-1,-1,-1,-1,-1,-1,-1,-1,-1,-1,-1,-1,-1,-1,-1,-1,-1,-1,-1,-1,-1,-1,-1,-1,-1,-1,-1,-1,-1,-1,-1,-1,-1,-1,-1,-1,-1,-1,-1,-1,-1,-1,-1,-1,-1,-1,-1,-1,-1,-1,-1,-1,-1,-1,-1,-1,-1,-1,-1,-1,-1,-1,-1,-1,-1,-1,-1,-1,-1,-1,-1,-1,-1,-1,-1,-1,-1,-1,-1,-1,-1,-1,-1,-1,-1,-1,-1,-1,-1,-1,-1,-1,-1,-1,-1,-1,-1,-1,-1,-1,-1,-1,-1,-1,-1,-1,-1,-1,-1,-1,-1,-1,-1,-1,-1,-1,-1,-1,-1,-1,-1,-1,-1,-1,-1,-1,-1,-1,-1,-1,-1,-1,-1,-1,-1,-1,-1,-1,-1,-1,-1,-1,-1,-1,-1,-1,-1,-1,-1,-1,-1,-1,-1,-1,-1,-1,-1,-1,-1,-1,-1,-1,-1,-1"
                    },
                    "to": {
                        "startLines": "26,32,34,166,167,168,169,171,172,173,174,175,176,177,178,179,180,181,182,183,184,185,186,187,188,215,216,217,218,219,220,221,222,223,224,226,227,228,229,230,231,232,233,234,235,236,237,249,250,251,252,253,254,255,256,257,258,259,260,261,262,263,264,265,266,267,268,269,270,271,272,273,274,275,276,277,278,279,280,281,282,283,284,285,286,287,288,289,290,291,292,293,294,295,296,297,298,299,300,301,302,303,304,305,306,307,308,309,310,311,312,313,314,315,316,317,318,319,320,321,322,323,324,325,326,327,328,329,330,331,332,333,334,335,336,337,338,339,340,341,342,343,398,399,403,404,405,406,407,408,409,478,479,480,481,482,483,484,485,488,489,490,491,493,500,501,507,522,524,525,528,529,541,542,543,544,545,546,547,548,549,550,551,552,553,554,555,556,557,558,559,560,561,562,563,564,565,566,567,568,569,570,571,572,573,574,575,576,577,578,579,659,667,668,669,670,671,682,690,691,695,699,710,715,721,728,732,736,741,745,749,753,757,761,765,771,775,781,785,791,795,800,804,807,811,817,821,827,831,837,840,844,848,852,856,860,861,862,863,866,869,872,875,879,880,881,882,883,886,888,890,892,897,898,902,908,912,913,915,926,927,931,937,941,992,993,997,1024,1028,1029,1033,1259,1426,1452,1620,1646,1677,1685,1691,1705,1727,1732,1737,1747,1756,1765,1769,1776,1784,1791,1792,1801,1804,1807,1811,1815,1819,1822,1823,1827,1831,1841,1846,1853,1859,1860,1863,1867,1872,1874,1876,1879,1882,1884,1888,1891,1898,1901,1904,1908,1910,1914,1916,1918,1920,1924,1932,1940,1952,1958,1967,1970,1981,1984,1989,1990,2074,2132,2195,2196,2206,2215,2216,2218,2222,2225,2228,2231,2234,2237,2240,2243,2247,2250,2253,2256,2260,2263,2267,2271,2272,2273,2274,2275,2276,2277,2278,2279,2280,2281,2282,2283,2284,2285,2286,2287,2288,2289,2290,2291,2293,2295,2296,2297,2298,2299,2300,2301,2302,2304,2305,2307,2308,2310,2312,2313,2315,2316,2317,2318,2319,2320,2322,2323,2324,2325,2326,2479,2481,2483,2485,2486,2487,2488,2489,2490,2491,2492,2493,2494,2495,2496,2497,2499,2500,2501,2502,2503,2504,2506,2510,2568,2569,2570,2571,2572,2573,2574,2597,2599,2601,2603,2605,2607,2608,2609,2610,2612,2614,2616,2617,2618,2619,2620,2621,2622,2623,2624,2625,2626,2627,2630,2631,2632,2633,2635,2637,2638,2640,2641,2643,2645,2647,2648,2649,2650,2651,2652,2653,2654,2655,2656,2657,2658,2660,2661,2662,2663,2665,2666,2667,2668,2669,2671,2673,2675,2677,2678,2679,2680,2681,2682,2683,2684,2685,2686,2687,2688,2689,2690",
                        "startColumns": "4,4,4,4,4,4,4,4,4,4,4,4,4,4,4,4,4,4,4,4,4,4,4,4,4,4,4,4,4,4,4,4,4,4,4,4,4,4,4,4,4,4,4,4,4,4,4,4,4,4,4,4,4,4,4,4,4,4,4,4,4,4,4,4,4,4,4,4,4,4,4,4,4,4,4,4,4,4,4,4,4,4,4,4,4,4,4,4,4,4,4,4,4,4,4,4,4,4,4,4,4,4,4,4,4,4,4,4,4,4,4,4,4,4,4,4,4,4,4,4,4,4,4,4,4,4,4,4,4,4,4,4,4,4,4,4,4,4,4,4,4,4,4,4,4,4,4,4,4,4,4,4,4,4,4,4,4,4,4,4,4,4,4,4,4,4,4,4,4,4,4,4,4,4,4,4,4,4,4,4,4,4,4,4,4,4,4,4,4,4,4,4,4,4,4,4,4,4,4,4,4,4,4,4,4,4,4,4,4,4,4,4,4,4,4,4,4,4,4,4,4,4,4,4,4,4,4,4,4,4,4,4,4,4,4,4,4,4,4,4,4,4,4,4,4,4,4,4,4,4,4,4,4,4,4,4,4,4,4,4,4,4,4,4,4,4,4,4,4,4,4,4,4,4,4,4,4,4,4,4,4,4,4,4,4,4,4,4,4,4,4,4,4,4,4,4,4,4,4,4,4,4,4,4,4,4,4,4,4,4,4,4,4,4,4,4,4,4,4,4,4,4,4,4,4,4,4,4,4,4,4,4,4,4,4,4,4,4,4,4,4,4,4,4,4,4,4,4,4,4,4,4,4,4,4,4,4,4,4,4,4,4,4,4,4,4,4,4,4,4,4,4,4,4,4,4,4,4,4,4,4,4,4,4,4,4,4,4,4,4,4,4,4,4,4,4,4,4,4,4,4,4,4,4,4,4,4,4,4,4,4,4,4,4,4,4,4,4,4,4,4,4,4,4,4,4,4,4,4,4,4,4,4,4,4,4,4,4,4,4,4,4,4,4,4,4,4,4,4,4,4,4,4,4,4,4,4,4,4,4,4,4,4,4,4,4,4,4,4,4,4,4,4,4,4,4,4,4,4,4,4,4,4,4,4,4,4,4,4,4,4,4,4,4,4,4,4,4,4,4,4,4,4,4,4,4,4,4,4,4,4,4,4,4,4,4,4,4,4,4,4,4,4,4,4,4,4,4,4,4",
                        "startOffsets": "1320,1547,1645,8062,8103,8158,8217,8341,8422,8483,8558,8634,8711,8789,8874,8956,9032,9108,9185,9263,9369,9475,9554,9634,9691,11576,11650,11725,11790,11856,11916,11977,12049,12122,12189,12314,12373,12432,12491,12550,12609,12663,12717,12770,12824,12878,12932,13759,13833,13912,13985,14059,14130,14202,14274,14347,14404,14462,14535,14609,14683,14758,14830,14903,14973,15044,15104,15165,15234,15303,15373,15447,15523,15587,15664,15740,15817,15882,15951,16028,16103,16172,16240,16317,16383,16444,16541,16606,16675,16774,16845,16904,16962,17019,17078,17142,17213,17285,17357,17429,17501,17568,17636,17704,17763,17826,17890,17980,18071,18131,18197,18264,18330,18400,18464,18517,18630,18688,18751,18816,18881,18956,19029,19101,19150,19211,19272,19333,19395,19459,19523,19587,19652,19715,19775,19836,19902,19961,20021,20083,20154,20214,23744,23830,24080,24170,24257,24345,24427,24510,24600,28858,28910,28968,29013,29079,29143,29200,29257,29459,29516,29564,29613,29704,30037,30084,30368,31095,31175,31239,31429,31489,32219,32293,32363,32441,32495,32565,32650,32698,32744,32815,32893,32971,33043,33117,33191,33265,33345,33418,33487,33559,33636,33697,33760,33826,33890,33961,34024,34089,34153,34214,34275,34327,34400,34474,34543,34618,34692,34766,34907,42343,42836,42914,43004,43092,43188,43837,44419,44508,44755,45036,45702,45987,46380,46857,47079,47301,47577,47804,48034,48264,48494,48724,48951,49370,49596,50021,50251,50679,50898,51181,51389,51520,51747,52173,52398,52825,53046,53471,53591,53867,54168,54492,54783,55097,55234,55365,55470,55712,55879,56083,56291,56562,56674,56786,56891,57008,57222,57368,57508,57594,57942,58030,58276,58694,58943,59025,59123,59715,59815,60067,60491,60746,64175,64264,64501,66525,66767,66869,67122,82873,93002,94518,104746,106274,108031,108657,109077,110138,111403,111659,111895,112442,112936,113541,113739,114319,114883,115258,115376,115914,116071,116267,116540,116796,116966,117107,117171,117453,117739,118415,118679,119017,119370,119464,119650,119956,120218,120343,120470,120709,120920,121039,121232,121409,121864,122045,122167,122426,122539,122726,122828,122935,123064,123339,123847,124343,125220,125514,126084,126233,126965,127137,127473,127565,131789,136071,140840,140902,141480,142064,142155,142268,142497,142657,142809,142980,143146,143315,143482,143645,143888,144058,144231,144402,144676,144875,145080,145410,145494,145590,145686,145784,145884,145986,146088,146190,146292,146394,146494,146590,146702,146831,146954,147085,147216,147314,147428,147522,147662,147796,147892,148004,148104,148220,148316,148428,148528,148668,148804,148968,149098,149256,149406,149547,149691,149826,149938,150088,150216,150344,150480,150612,150742,150872,150984,159465,159611,159755,159893,159959,160049,160125,160229,160319,160421,160529,160637,160737,160817,160909,161007,161117,161195,161301,161393,161497,161607,161729,161892,165611,165691,165791,165881,165991,166085,166191,167889,167989,168101,168215,168331,168447,168541,168655,168767,168869,168989,169111,169193,169297,169417,169543,169641,169735,169823,169935,170051,170173,170285,170460,170576,170662,170754,170866,170990,171057,171183,171251,171379,171523,171651,171720,171815,171930,172043,172142,172251,172362,172473,172574,172679,172779,172909,173000,173123,173217,173329,173415,173519,173615,173703,173821,173925,174029,174155,174243,174351,174451,174541,174651,174735,174837,174921,174975,175039,175145,175255,175339",
                        "endLines": "26,32,34,166,167,168,169,171,172,173,174,175,176,177,178,179,180,181,182,183,184,185,186,187,188,215,216,217,218,219,220,221,222,223,224,226,227,228,229,230,231,232,233,234,235,236,237,249,250,251,252,253,254,255,256,257,258,259,260,261,262,263,264,265,266,267,268,269,270,271,272,273,274,275,276,277,278,279,280,281,282,283,284,285,286,287,288,289,290,291,292,293,294,295,296,297,298,299,300,301,302,303,304,305,306,307,308,309,310,311,312,313,314,315,316,317,318,319,320,321,322,323,324,325,326,327,328,329,330,331,332,333,334,335,336,337,338,339,340,341,342,343,398,399,403,404,405,406,407,408,409,478,479,480,481,482,483,484,485,488,489,490,491,493,500,501,507,522,524,525,528,529,541,542,543,544,545,546,547,548,549,550,551,552,553,554,555,556,557,558,559,560,561,562,563,564,565,566,567,568,569,570,571,572,573,574,575,576,577,578,579,659,667,668,669,670,671,689,690,694,698,702,714,720,727,731,735,740,744,748,752,756,760,764,770,774,780,784,790,794,799,803,806,810,816,820,826,830,836,839,843,847,851,855,859,860,861,862,865,868,871,874,878,879,880,881,882,885,887,889,891,896,897,901,907,911,912,914,925,926,930,936,940,941,992,996,1023,1027,1028,1032,1060,1425,1451,1619,1645,1676,1684,1690,1704,1726,1731,1736,1746,1755,1764,1768,1775,1783,1790,1791,1800,1803,1806,1810,1814,1818,1821,1822,1826,1830,1840,1845,1852,1858,1859,1862,1866,1871,1873,1875,1878,1881,1883,1887,1890,1897,1900,1903,1907,1909,1913,1915,1917,1919,1923,1931,1939,1951,1957,1966,1969,1980,1983,1988,1989,1994,2131,2190,2195,2205,2214,2215,2217,2221,2224,2227,2230,2233,2236,2239,2242,2246,2249,2252,2255,2259,2262,2266,2270,2271,2272,2273,2274,2275,2276,2277,2278,2279,2280,2281,2282,2283,2284,2285,2286,2287,2288,2289,2290,2292,2294,2295,2296,2297,2298,2299,2300,2301,2303,2304,2306,2307,2309,2311,2312,2314,2315,2316,2317,2318,2319,2321,2322,2323,2324,2325,2326,2480,2482,2484,2485,2486,2487,2488,2489,2490,2491,2492,2493,2494,2495,2496,2498,2499,2500,2501,2502,2503,2505,2509,2513,2568,2569,2570,2571,2572,2573,2574,2598,2600,2602,2604,2606,2607,2608,2609,2611,2613,2615,2616,2617,2618,2619,2620,2621,2622,2623,2624,2625,2626,2629,2630,2631,2632,2634,2636,2637,2639,2640,2642,2644,2646,2647,2648,2649,2650,2651,2652,2653,2654,2655,2656,2657,2659,2660,2661,2662,2664,2665,2666,2667,2668,2670,2672,2674,2676,2677,2678,2679,2680,2681,2682,2683,2684,2685,2686,2687,2688,2689,2690",
                        "endColumns": "54,44,48,40,54,58,61,80,60,74,75,76,77,84,81,75,75,76,77,105,105,78,79,56,57,73,74,64,65,59,60,71,72,66,67,58,58,58,58,58,53,53,52,53,53,53,53,73,78,72,73,70,71,71,72,56,57,72,73,73,74,71,72,69,70,59,60,68,68,69,73,75,63,76,75,76,64,68,76,74,68,67,76,65,60,96,64,68,98,70,58,57,56,58,63,70,71,71,71,71,66,67,67,58,62,63,89,90,59,65,66,65,69,63,52,112,57,62,64,64,74,72,71,48,60,60,60,61,63,63,63,64,62,59,60,65,58,59,61,70,59,67,85,86,89,86,87,81,82,89,90,51,57,44,65,63,56,56,53,56,47,48,50,33,46,48,45,31,63,61,59,56,73,69,77,53,69,84,47,45,70,77,77,71,73,73,73,79,72,68,71,76,60,62,65,63,70,62,64,63,60,60,51,72,73,68,74,73,73,140,69,52,77,89,87,95,89,12,88,12,12,12,12,12,12,12,12,12,12,12,12,12,12,12,12,12,12,12,12,12,12,12,12,12,12,12,12,12,12,12,12,12,12,12,12,136,130,104,12,12,12,12,12,111,111,104,116,12,12,12,12,12,87,12,12,12,81,12,12,99,12,12,12,93,88,12,12,12,101,12,12,12,12,12,12,12,12,12,12,12,12,12,12,12,12,12,12,12,12,117,12,12,12,12,12,12,12,63,12,12,12,12,12,12,93,12,12,12,12,12,12,12,12,12,12,12,12,12,12,12,12,12,12,12,12,12,12,12,12,12,12,12,12,12,91,12,12,12,61,12,12,90,12,12,12,12,12,12,12,12,12,12,12,12,12,12,12,12,12,83,95,95,97,99,101,101,101,101,101,99,95,111,128,122,130,130,97,113,93,12,12,95,111,99,115,95,111,99,12,135,12,129,12,12,140,12,134,111,149,127,127,12,131,129,129,111,139,12,12,12,65,89,75,103,89,101,107,107,99,79,91,97,12,77,105,91,103,109,12,12,12,79,99,89,109,93,105,91,12,12,12,12,12,93,113,111,12,12,12,81,103,119,125,97,93,87,111,115,121,111,12,115,85,91,12,12,66,12,67,12,12,12,68,94,114,112,98,108,110,110,100,104,99,12,90,122,93,12,85,103,95,87,12,12,12,12,87,107,99,89,109,83,101,83,53,63,105,109,83,119",
                        "endOffsets": "1370,1587,1689,8098,8153,8212,8274,8417,8478,8553,8629,8706,8784,8869,8951,9027,9103,9180,9258,9364,9470,9549,9629,9686,9744,11645,11720,11785,11851,11911,11972,12044,12117,12184,12252,12368,12427,12486,12545,12604,12658,12712,12765,12819,12873,12927,12981,13828,13907,13980,14054,14125,14197,14269,14342,14399,14457,14530,14604,14678,14753,14825,14898,14968,15039,15099,15160,15229,15298,15368,15442,15518,15582,15659,15735,15812,15877,15946,16023,16098,16167,16235,16312,16378,16439,16536,16601,16670,16769,16840,16899,16957,17014,17073,17137,17208,17280,17352,17424,17496,17563,17631,17699,17758,17821,17885,17975,18066,18126,18192,18259,18325,18395,18459,18512,18625,18683,18746,18811,18876,18951,19024,19096,19145,19206,19267,19328,19390,19454,19518,19582,19647,19710,19770,19831,19897,19956,20016,20078,20149,20209,20277,23825,23912,24165,24252,24340,24422,24505,24595,24686,28905,28963,29008,29074,29138,29195,29252,29306,29511,29559,29608,29659,29733,30079,30128,30409,31122,31234,31296,31484,31541,32288,32358,32436,32490,32560,32645,32693,32739,32810,32888,32966,33038,33112,33186,33260,33340,33413,33482,33554,33631,33692,33755,33821,33885,33956,34019,34084,34148,34209,34270,34322,34395,34469,34538,34613,34687,34761,34902,34972,42391,42909,42999,43087,43183,43273,44414,44503,44750,45031,45283,45982,46375,46852,47074,47296,47572,47799,48029,48259,48489,48719,48946,49365,49591,50016,50246,50674,50893,51176,51384,51515,51742,52168,52393,52820,53041,53466,53586,53862,54163,54487,54778,55092,55229,55360,55465,55707,55874,56078,56286,56557,56669,56781,56886,57003,57217,57363,57503,57589,57937,58025,58271,58689,58938,59020,59118,59710,59810,60062,60486,60741,60835,64259,64496,66520,66762,66864,67117,69273,92997,94513,104741,106269,108026,108652,109072,110133,111398,111654,111890,112437,112931,113536,113734,114314,114878,115253,115371,115909,116066,116262,116535,116791,116961,117102,117166,117448,117734,118410,118674,119012,119365,119459,119645,119951,120213,120338,120465,120704,120915,121034,121227,121404,121859,122040,122162,122421,122534,122721,122823,122930,123059,123334,123842,124338,125215,125509,126079,126228,126960,127132,127468,127560,127838,136066,140491,140897,141475,142059,142150,142263,142492,142652,142804,142975,143141,143310,143477,143640,143883,144053,144226,144397,144671,144870,145075,145405,145489,145585,145681,145779,145879,145981,146083,146185,146287,146389,146489,146585,146697,146826,146949,147080,147211,147309,147423,147517,147657,147791,147887,147999,148099,148215,148311,148423,148523,148663,148799,148963,149093,149251,149401,149542,149686,149821,149933,150083,150211,150339,150475,150607,150737,150867,150979,151119,159606,159750,159888,159954,160044,160120,160224,160314,160416,160524,160632,160732,160812,160904,161002,161112,161190,161296,161388,161492,161602,161724,161887,162044,165686,165786,165876,165986,166080,166186,166278,167984,168096,168210,168326,168442,168536,168650,168762,168864,168984,169106,169188,169292,169412,169538,169636,169730,169818,169930,170046,170168,170280,170455,170571,170657,170749,170861,170985,171052,171178,171246,171374,171518,171646,171715,171810,171925,172038,172137,172246,172357,172468,172569,172674,172774,172904,172995,173118,173212,173324,173410,173514,173610,173698,173816,173920,174024,174150,174238,174346,174446,174536,174646,174730,174832,174916,174970,175034,175140,175250,175334,175454"
                    }
                },
                {
                    "source": "C:\\Users\\Dicky Adhadyanto\\.gradle\\caches\\transforms-2\\files-2.1\\f58c98609d18fa4939d28278c71ddd10\\res\\values\\values.xml",
                    "from": {
                        "startLines": "-1,-1,-1,-1,-1,-1,-1,-1,-1,-1,-1,-1,-1,-1,-1,-1,-1,-1,-1,-1,-1,-1,-1,-1,-1",
                        "startColumns": "-1,-1,-1,-1,-1,-1,-1,-1,-1,-1,-1,-1,-1,-1,-1,-1,-1,-1,-1,-1,-1,-1,-1,-1,-1",
                        "startOffsets": "-1,-1,-1,-1,-1,-1,-1,-1,-1,-1,-1,-1,-1,-1,-1,-1,-1,-1,-1,-1,-1,-1,-1,-1,-1"
                    },
                    "to": {
                        "startLines": "196,197,198,199,200,201,202,203,590,591,592,593,594,595,596,597,599,600,601,602,603,604,605,606,607",
                        "startColumns": "4,4,4,4,4,4,4,4,4,4,4,4,4,4,4,4,4,4,4,4,4,4,4,4,4",
                        "startOffsets": "10142,10232,10312,10402,10492,10572,10653,10733,35771,35876,36057,36182,36289,36469,36592,36708,36978,37166,37271,37452,37577,37752,37900,37963,38025",
                        "endColumns": "89,79,89,89,79,80,79,79,104,180,124,106,179,122,115,102,187,104,180,124,174,147,62,61,78",
                        "endOffsets": "10227,10307,10397,10487,10567,10648,10728,10808,35871,36052,36177,36284,36464,36587,36703,36806,37161,37266,37447,37572,37747,37895,37958,38020,38099"
                    }
                },
                {
                    "source": "C:\\Users\\Dicky Adhadyanto\\AndroidStudioProjects\\IndoTrucker\\app\\src\\main\\res\\values\\ic_launcher_background.xml",
                    "from": {
                        "startLines": "-1",
                        "startColumns": "-1",
                        "startOffsets": "-1"
                    },
                    "to": {
                        "startLines": "225",
                        "startColumns": "4",
                        "startOffsets": "12257",
                        "endColumns": "56",
                        "endOffsets": "12309"
                    }
                },
                {
                    "source": "C:\\Users\\Dicky Adhadyanto\\AndroidStudioProjects\\IndoTrucker\\app\\src\\main\\res\\values\\colors.xml",
                    "from": {
                        "startLines": "-1,-1,-1",
                        "startColumns": "-1,-1,-1",
                        "startOffsets": "-1,-1,-1"
                    },
                    "to": {
                        "startLines": "193,194,195",
                        "startColumns": "4,4,4",
                        "startOffsets": "9998,10044,10091",
                        "endColumns": "45,46,50",
                        "endOffsets": "10039,10086,10137"
                    }
                },
                {
                    "source": "C:\\Users\\Dicky Adhadyanto\\.gradle\\caches\\transforms-2\\files-2.1\\ed5e074bc753091978f4075effb7d167\\res\\values\\values.xml",
                    "from": {
                        "startLines": "-1,-1,-1,-1,-1,-1,-1,-1,-1,-1,-1,-1,-1,-1,-1,-1,-1,-1,-1,-1,-1,-1,-1,-1,-1,-1,-1,-1,-1,-1,-1,-1,-1,-1,-1,-1,-1,-1,-1,-1,-1,-1,-1,-1,-1,-1,-1,-1,-1,-1,-1,-1,-1,-1,-1,-1,-1",
                        "startColumns": "-1,-1,-1,-1,-1,-1,-1,-1,-1,-1,-1,-1,-1,-1,-1,-1,-1,-1,-1,-1,-1,-1,-1,-1,-1,-1,-1,-1,-1,-1,-1,-1,-1,-1,-1,-1,-1,-1,-1,-1,-1,-1,-1,-1,-1,-1,-1,-1,-1,-1,-1,-1,-1,-1,-1,-1,-1",
                        "startOffsets": "-1,-1,-1,-1,-1,-1,-1,-1,-1,-1,-1,-1,-1,-1,-1,-1,-1,-1,-1,-1,-1,-1,-1,-1,-1,-1,-1,-1,-1,-1,-1,-1,-1,-1,-1,-1,-1,-1,-1,-1,-1,-1,-1,-1,-1,-1,-1,-1,-1,-1,-1,-1,-1,-1,-1,-1,-1"
                    },
                    "to": {
                        "startLines": "2,3,16,22,23,24,27,35,36,37,38,41,42,45,48,49,50,51,52,55,58,59,60,61,66,69,72,73,74,79,80,81,84,87,88,91,94,97,100,101,104,107,108,113,114,119,122,125,126,127,128,129,130,131,132,133,134",
                        "startColumns": "4,4,4,4,4,4,4,4,4,4,4,4,4,4,4,4,4,4,4,4,4,4,4,4,4,4,4,4,4,4,4,4,4,4,4,4,4,4,4,4,4,4,4,4,4,4,4,4,4,4,4,4,4,4,4,4,4",
                        "startOffsets": "150,211,786,1100,1152,1213,1375,1694,1755,1815,1885,2018,2086,2215,2341,2403,2468,2536,2603,2726,2851,2918,2983,3048,3229,3350,3471,3537,3604,3814,3883,3949,4074,4200,4267,4393,4520,4645,4772,4837,4963,5086,5151,5359,5426,5606,5726,5846,5911,5973,6035,6097,6156,6216,6277,6338,6397",
                        "endLines": "2,10,16,22,23,24,30,35,36,37,40,41,44,47,48,49,50,51,54,57,58,59,60,65,68,71,72,73,78,79,80,83,86,87,90,93,96,99,100,103,106,107,112,113,118,121,124,125,126,127,128,129,130,131,132,133,142",
                        "endColumns": "60,11,47,51,60,45,11,60,59,69,11,67,11,11,61,64,67,66,11,11,66,64,64,11,11,11,65,66,11,68,65,11,11,66,11,11,11,11,64,11,11,64,11,66,11,11,11,64,61,61,61,58,59,60,60,58,11",
                        "endOffsets": "206,497,829,1147,1208,1254,1497,1750,1810,1880,2013,2081,2210,2336,2398,2463,2531,2598,2721,2846,2913,2978,3043,3224,3345,3466,3532,3599,3809,3878,3944,4069,4195,4262,4388,4515,4640,4767,4832,4958,5081,5146,5354,5421,5601,5721,5841,5906,5968,6030,6092,6151,6211,6272,6333,6392,6734"
                    }
                },
                {
                    "source": "C:\\Users\\Dicky Adhadyanto\\.gradle\\caches\\transforms-2\\files-2.1\\7184c7782cd85117bd63b4c5a04b40f0\\res\\values\\values.xml",
                    "from": {
                        "startLines": "-1,-1,-1,-1,-1,-1,-1",
                        "startColumns": "-1,-1,-1,-1,-1,-1,-1",
                        "startOffsets": "-1,-1,-1,-1,-1,-1,-1"
                    },
                    "to": {
                        "startLines": "400,401,402,410,411,412,494",
                        "startColumns": "4,4,4,4,4,4,4",
                        "startOffsets": "23917,23976,24024,24691,24766,24842,29738",
                        "endColumns": "58,47,55,74,75,71,65",
                        "endOffsets": "23971,24019,24075,24761,24837,24909,29799"
                    }
                },
                {
                    "source": "C:\\Users\\Dicky Adhadyanto\\.gradle\\caches\\transforms-2\\files-2.1\\089667e2325ae2f0ad2bd656ca82b327\\res\\values\\values.xml",
                    "from": {
                        "startLines": "-1,-1",
                        "startColumns": "-1,-1",
                        "startOffsets": "-1,-1"
                    },
                    "to": {
                        "startLines": "25,2944",
                        "startColumns": "4,4",
                        "startOffsets": "1259,190720",
                        "endLines": "25,2946",
                        "endColumns": "60,12",
                        "endOffsets": "1315,190860"
                    }
                },
                {
                    "source": "C:\\Users\\Dicky Adhadyanto\\AndroidStudioProjects\\IndoTrucker\\app\\build\\generated\\res\\google-services\\debug\\values\\values.xml",
                    "from": {
                        "startLines": "-1,-1,-1,-1,-1,-1,-1,-1",
                        "startColumns": "-1,-1,-1,-1,-1,-1,-1,-1",
                        "startOffsets": "-1,-1,-1,-1,-1,-1,-1,-1"
                    },
                    "to": {
                        "startLines": "621,628,629,630,631,632,633,658",
                        "startColumns": "4,4,4,4,4,4,4,4",
                        "startOffsets": "38950,39640,39752,39834,39938,40041,40161,42265",
                        "endColumns": "143,111,81,103,102,119,100,77",
                        "endOffsets": "39089,39747,39829,39933,40036,40156,40257,42338"
                    }
                },
                {
                    "source": "C:\\Users\\Dicky Adhadyanto\\.gradle\\caches\\transforms-2\\files-2.1\\a31959e7cd4d01cb208866f2311eee93\\res\\values\\values.xml",
                    "from": {
                        "startLines": "-1,-1,-1,-1,-1,-1,-1,-1,-1,-1",
                        "startColumns": "-1,-1,-1,-1,-1,-1,-1,-1,-1,-1",
                        "startOffsets": "-1,-1,-1,-1,-1,-1,-1,-1,-1,-1"
                    },
                    "to": {
                        "startLines": "492,499,502,503,504,517,518,519,520,521",
                        "startColumns": "4,4,4,4,4,4,4,4,4,4",
                        "startOffsets": "29664,29994,30133,30180,30235,30829,30883,30935,30984,31045",
                        "endColumns": "39,42,46,54,44,53,51,48,60,49",
                        "endOffsets": "29699,30032,30175,30230,30275,30878,30930,30979,31040,31090"
                    }
                },
                {
                    "source": "C:\\Users\\Dicky Adhadyanto\\AndroidStudioProjects\\IndoTrucker\\app\\src\\main\\res\\values\\strings.xml",
                    "from": {
                        "startLines": "-1,-1,-1,-1,-1,-1,-1,-1,-1,-1,-1,-1,-1,-1,-1,-1,-1,-1,-1,-1,-1,-1,-1,-1,-1,-1,-1,-1,-1,-1,-1,-1,-1,-1,-1,-1,39",
                        "startColumns": "-1,-1,-1,-1,-1,-1,-1,-1,-1,-1,-1,-1,-1,-1,-1,-1,-1,-1,-1,-1,-1,-1,-1,-1,-1,-1,-1,-1,-1,-1,-1,-1,-1,-1,-1,-1,4",
                        "startOffsets": "-1,-1,-1,-1,-1,-1,-1,-1,-1,-1,-1,-1,-1,-1,-1,-1,-1,-1,-1,-1,-1,-1,-1,-1,-1,-1,-1,-1,-1,-1,-1,-1,-1,-1,-1,-1,2111",
                        "endColumns": "-1,-1,-1,-1,-1,-1,-1,-1,-1,-1,-1,-1,-1,-1,-1,-1,-1,-1,-1,-1,-1,-1,-1,-1,-1,-1,-1,-1,-1,-1,-1,-1,-1,-1,-1,-1,55",
                        "endOffsets": "-1,-1,-1,-1,-1,-1,-1,-1,-1,-1,-1,-1,-1,-1,-1,-1,-1,-1,-1,-1,-1,-1,-1,-1,-1,-1,-1,-1,-1,-1,-1,-1,-1,-1,-1,-1,2162"
                    },
                    "to": {
                        "startLines": "540,580,581,582,583,584,589,608,609,610,619,620,622,623,624,634,635,637,638,639,640,641,642,643,644,646,647,648,649,650,657,661,662,663,664,665,666",
                        "startColumns": "4,4,4,4,4,4,4,4,4,4,4,4,4,4,4,4,4,4,4,4,4,4,4,4,4,4,4,4,4,4,4,4,4,4,4,4,4",
                        "startOffsets": "32178,34977,35039,35081,35129,35199,35720,38104,38161,38219,38844,38912,39094,39148,39188,40262,40332,40587,40641,40689,40737,40785,40829,40869,40941,41076,41118,41156,41214,41281,42203,42467,42526,42578,42646,42704,42780",
                        "endColumns": "40,61,41,47,69,48,50,56,57,56,67,37,53,39,55,69,101,53,47,47,47,43,39,71,53,41,37,57,66,45,61,58,51,67,57,75,55",
                        "endOffsets": "32214,35034,35076,35124,35194,35243,35766,38156,38214,38271,38907,38945,39143,39183,39239,40327,40429,40636,40684,40732,40780,40824,40864,40936,40990,41113,41151,41209,41276,41322,42260,42521,42573,42641,42699,42775,42831"
                    }
                },
                {
                    "source": "C:\\Users\\Dicky Adhadyanto\\.gradle\\caches\\transforms-2\\files-2.1\\ea3ff9733c60c07f3213b60695b9238c\\res\\values\\values.xml",
                    "from": {
                        "startLines": "-1,-1",
                        "startColumns": "-1,-1",
                        "startOffsets": "-1,-1"
                    },
                    "to": {
                        "startLines": "532,598",
                        "startColumns": "4,4",
                        "startOffsets": "31681,36811",
                        "endColumns": "67,166",
                        "endOffsets": "31744,36973"
                    }
                },
                {
                    "source": "C:\\Users\\Dicky Adhadyanto\\.gradle\\caches\\transforms-2\\files-2.1\\ba2c701919a0d360a513334f1f434a46\\res\\values\\values.xml",
                    "from": {
                        "startLines": "-1,-1,-1,-1,-1,-1,-1,-1,-1,-1,-1,-1",
                        "startColumns": "-1,-1,-1,-1,-1,-1,-1,-1,-1,-1,-1,-1",
                        "startOffsets": "-1,-1,-1,-1,-1,-1,-1,-1,-1,-1,-1,-1"
                    },
                    "to": {
                        "startLines": "15,189,190,191,192,344,345,346,703,2066,2068,2071",
                        "startColumns": "4,4,4,4,4,4,4,4,4,4,4,4",
                        "startOffsets": "734,9749,9810,9872,9934,20282,20341,20398,45288,131471,131535,131661",
                        "endLines": "15,189,190,191,192,344,345,346,709,2067,2070,2073",
                        "endColumns": "51,60,61,61,63,58,56,53,12,12,12,12",
                        "endOffsets": "781,9805,9867,9929,9993,20336,20393,20447,45697,131530,131656,131784"
                    }
                },
                {
                    "source": "C:\\Users\\Dicky Adhadyanto\\AndroidStudioProjects\\IndoTrucker\\app\\src\\main\\res\\values\\styles.xml",
                    "from": {
                        "startLines": "-1",
                        "startColumns": "-1",
                        "startOffsets": "-1"
                    },
                    "to": {
                        "startLines": "676",
                        "startColumns": "4",
                        "startOffsets": "43555",
                        "endLines": "681",
                        "endColumns": "12",
                        "endOffsets": "43832"
                    }
                },
                {
                    "source": "C:\\Users\\Dicky Adhadyanto\\.gradle\\caches\\transforms-2\\files-2.1\\6924d5e5e2f9fa8c046f018684194a90\\res\\values\\values.xml",
                    "from": {
                        "startLines": "-1,-1,-1,-1,-1,-1,-1,-1,-1,-1,-1,-1,-1,-1,-1,-1,-1,-1,-1,-1,-1,-1,-1,-1,-1,-1,-1,-1,-1,-1,-1,-1,-1,-1,-1,-1,-1,-1,-1,-1,-1,-1,-1,-1,-1,-1,-1,-1,-1,-1,-1,-1,-1,-1,-1,-1,-1,-1,-1,-1,-1,-1,-1,-1,-1,-1,-1,-1,-1,-1,-1,-1,-1,-1,-1,-1,-1,-1,-1,-1,-1,-1,-1,-1,-1,-1,-1,-1,-1,-1,-1,-1,-1,-1,-1,-1,-1,-1,-1,-1,-1,-1,-1,-1,-1,-1,-1,-1,-1,-1,-1,-1,-1,-1,-1,-1,-1,-1,-1,-1,-1,-1,-1,-1,-1,-1,-1,-1,-1,-1,-1,-1,-1,-1,-1,-1,-1,-1,-1,-1,-1,-1,-1,-1,-1,-1,-1,-1,-1,-1,-1,-1,-1,-1,-1,-1,-1,-1,-1,-1,-1,-1,-1,-1,-1,-1,-1,-1,-1,-1,-1,-1,-1,-1,-1,-1,-1,-1,-1,-1,-1,-1,-1,-1,-1,-1,-1,-1,-1,-1,-1,-1,-1,-1,-1,-1,-1,-1,-1,-1,-1,-1,-1,-1,-1,-1,-1,-1,-1,-1,-1,-1,-1,-1,-1,-1,-1,-1,-1,-1,-1,-1,-1,-1,-1,-1,-1,-1,-1,-1,-1,-1,-1,-1,-1,-1,-1,-1,-1,-1,-1,-1,-1,-1,-1,-1,-1,-1,-1,-1,-1,-1,-1,-1,-1,-1,-1,-1,-1,-1,-1,-1,-1,-1,-1,-1,-1,-1,-1,-1,-1,-1,-1,-1,-1,-1,-1,-1,-1,-1,-1,-1,-1,-1,-1,-1,-1,-1,-1,-1,-1,-1,-1,-1,-1,-1,-1,-1,-1,-1,-1,-1,-1,-1,-1,-1",
                        "startColumns": "-1,-1,-1,-1,-1,-1,-1,-1,-1,-1,-1,-1,-1,-1,-1,-1,-1,-1,-1,-1,-1,-1,-1,-1,-1,-1,-1,-1,-1,-1,-1,-1,-1,-1,-1,-1,-1,-1,-1,-1,-1,-1,-1,-1,-1,-1,-1,-1,-1,-1,-1,-1,-1,-1,-1,-1,-1,-1,-1,-1,-1,-1,-1,-1,-1,-1,-1,-1,-1,-1,-1,-1,-1,-1,-1,-1,-1,-1,-1,-1,-1,-1,-1,-1,-1,-1,-1,-1,-1,-1,-1,-1,-1,-1,-1,-1,-1,-1,-1,-1,-1,-1,-1,-1,-1,-1,-1,-1,-1,-1,-1,-1,-1,-1,-1,-1,-1,-1,-1,-1,-1,-1,-1,-1,-1,-1,-1,-1,-1,-1,-1,-1,-1,-1,-1,-1,-1,-1,-1,-1,-1,-1,-1,-1,-1,-1,-1,-1,-1,-1,-1,-1,-1,-1,-1,-1,-1,-1,-1,-1,-1,-1,-1,-1,-1,-1,-1,-1,-1,-1,-1,-1,-1,-1,-1,-1,-1,-1,-1,-1,-1,-1,-1,-1,-1,-1,-1,-1,-1,-1,-1,-1,-1,-1,-1,-1,-1,-1,-1,-1,-1,-1,-1,-1,-1,-1,-1,-1,-1,-1,-1,-1,-1,-1,-1,-1,-1,-1,-1,-1,-1,-1,-1,-1,-1,-1,-1,-1,-1,-1,-1,-1,-1,-1,-1,-1,-1,-1,-1,-1,-1,-1,-1,-1,-1,-1,-1,-1,-1,-1,-1,-1,-1,-1,-1,-1,-1,-1,-1,-1,-1,-1,-1,-1,-1,-1,-1,-1,-1,-1,-1,-1,-1,-1,-1,-1,-1,-1,-1,-1,-1,-1,-1,-1,-1,-1,-1,-1,-1,-1,-1,-1,-1,-1,-1,-1,-1,-1,-1,-1,-1,-1,-1,-1,-1,-1",
                        "startOffsets": "-1,-1,-1,-1,-1,-1,-1,-1,-1,-1,-1,-1,-1,-1,-1,-1,-1,-1,-1,-1,-1,-1,-1,-1,-1,-1,-1,-1,-1,-1,-1,-1,-1,-1,-1,-1,-1,-1,-1,-1,-1,-1,-1,-1,-1,-1,-1,-1,-1,-1,-1,-1,-1,-1,-1,-1,-1,-1,-1,-1,-1,-1,-1,-1,-1,-1,-1,-1,-1,-1,-1,-1,-1,-1,-1,-1,-1,-1,-1,-1,-1,-1,-1,-1,-1,-1,-1,-1,-1,-1,-1,-1,-1,-1,-1,-1,-1,-1,-1,-1,-1,-1,-1,-1,-1,-1,-1,-1,-1,-1,-1,-1,-1,-1,-1,-1,-1,-1,-1,-1,-1,-1,-1,-1,-1,-1,-1,-1,-1,-1,-1,-1,-1,-1,-1,-1,-1,-1,-1,-1,-1,-1,-1,-1,-1,-1,-1,-1,-1,-1,-1,-1,-1,-1,-1,-1,-1,-1,-1,-1,-1,-1,-1,-1,-1,-1,-1,-1,-1,-1,-1,-1,-1,-1,-1,-1,-1,-1,-1,-1,-1,-1,-1,-1,-1,-1,-1,-1,-1,-1,-1,-1,-1,-1,-1,-1,-1,-1,-1,-1,-1,-1,-1,-1,-1,-1,-1,-1,-1,-1,-1,-1,-1,-1,-1,-1,-1,-1,-1,-1,-1,-1,-1,-1,-1,-1,-1,-1,-1,-1,-1,-1,-1,-1,-1,-1,-1,-1,-1,-1,-1,-1,-1,-1,-1,-1,-1,-1,-1,-1,-1,-1,-1,-1,-1,-1,-1,-1,-1,-1,-1,-1,-1,-1,-1,-1,-1,-1,-1,-1,-1,-1,-1,-1,-1,-1,-1,-1,-1,-1,-1,-1,-1,-1,-1,-1,-1,-1,-1,-1,-1,-1,-1,-1,-1,-1,-1,-1,-1,-1,-1,-1,-1,-1,-1,-1"
                    },
                    "to": {
                        "startLines": "11,12,13,14,17,18,19,20,21,31,33,143,144,145,146,147,148,149,150,151,152,153,154,155,156,157,158,159,160,161,162,163,164,165,170,204,205,206,207,208,209,210,211,212,213,214,238,239,240,241,242,243,244,245,354,355,356,357,358,359,360,361,362,363,364,365,366,367,368,369,370,371,372,373,374,375,376,377,378,379,380,381,382,383,384,385,386,387,388,389,390,391,392,393,394,395,396,397,413,414,415,416,417,418,419,420,421,422,423,424,425,426,427,428,429,430,431,432,433,434,435,436,437,438,439,440,441,442,443,444,445,446,447,448,449,450,451,452,453,454,455,456,457,458,497,498,505,506,513,514,515,523,526,527,530,531,533,534,535,536,537,538,585,586,587,588,625,626,636,645,651,652,653,654,655,672,942,943,948,949,953,959,963,964,965,976,977,981,987,991,1061,1062,1063,1111,1157,1205,1251,1255,1995,2009,2048,2056,2191,2192,2193,2194,2343,2346,2347,2350,2353,2354,2357,2361,2366,2373,2380,2383,2384,2387,2388,2396,2403,2407,2414,2421,2428,2435,2442,2450,2458,2465,2473,2476,2514,2516,2521,2523,2528,2532,2536,2537,2542,2543,2544,2545,2546,2548,2549,2554,2555,2556,2557,2558,2560,2564,2575,2576,2577,2578,2579,2580,2581,2582,2583,2586,2590,2593,2693,2701,2708,2717,2721,2736,2744,2747,2756,2761,2772,2781,2784,2795,2805,2806,2827,2833,2842,2845,2848,2852,2855,2864,2867,2875,2880,2888,2893,2902,2909,2913,2917,2918,2922,2930,2934,2939",
                        "startColumns": "4,4,4,4,4,4,4,4,4,4,4,4,4,4,4,4,4,4,4,4,4,4,4,4,4,4,4,4,4,4,4,4,4,4,4,4,4,4,4,4,4,4,4,4,4,4,4,4,4,4,4,4,4,4,4,4,4,4,4,4,4,4,4,4,4,4,4,4,4,4,4,4,4,4,4,4,4,4,4,4,4,4,4,4,4,4,4,4,4,4,4,4,4,4,4,4,4,4,4,4,4,4,4,4,4,4,4,4,4,4,4,4,4,4,4,4,4,4,4,4,4,4,4,4,4,4,4,4,4,4,4,4,4,4,4,4,4,4,4,4,4,4,4,4,4,4,4,4,4,4,4,4,4,4,4,4,4,4,4,4,4,4,4,4,4,4,4,4,4,4,4,4,4,4,4,4,4,4,4,4,4,4,4,4,4,4,4,4,4,4,4,4,4,4,4,4,4,4,4,4,4,4,4,4,4,4,4,4,4,4,4,4,4,4,4,4,4,4,4,4,4,4,4,4,4,4,4,4,4,4,4,4,4,4,4,4,4,4,4,4,4,4,4,4,4,4,4,4,4,4,4,4,4,4,4,4,4,4,4,4,4,4,4,4,4,4,4,4,4,4,4,4,4,4,4,4,4,4,4,4,4,4,4,4,4,4,4,4,4,4,4,4,4,4,4,4,4,4,4,4,4,4,4,4,4,4",
                        "startOffsets": "502,558,618,679,834,887,945,993,1051,1502,1592,6739,6797,6857,6915,6961,7021,7074,7120,7170,7217,7275,7333,7392,7452,7514,7576,7638,7700,7762,7824,7885,7947,8009,8279,10813,10887,10950,11018,11099,11163,11229,11299,11369,11439,11509,12986,13049,13114,13180,13233,13309,13375,13462,20940,20994,21073,21151,21224,21289,21352,21418,21489,21560,21622,21691,21757,21824,21891,21947,21998,22051,22103,22157,22228,22291,22350,22412,22471,22544,22611,22671,22734,22809,22881,22952,23008,23079,23136,23193,23259,23323,23394,23451,23504,23567,23619,23677,24914,24980,25046,25127,25202,25258,25329,25403,25456,25517,25575,25625,25674,25723,25772,25824,25869,25950,26004,26057,26111,26162,26211,26262,26323,26384,26446,26496,26537,26587,26635,26697,26748,26797,26866,26927,26983,27054,27119,27182,27252,27321,27391,27453,27523,27593,29874,29932,30280,30325,30651,30698,30743,31127,31301,31367,31546,31609,31749,31806,31863,31923,31981,32051,35248,35398,35529,35633,39244,39401,40434,40995,41327,41405,41706,41872,42027,43278,60840,60933,61276,61383,61612,62021,62253,62353,62458,63056,63175,63410,63825,64063,69278,69399,69532,72804,75975,79244,82412,82636,127843,128647,130306,130756,140496,140569,140656,140741,152264,152459,152551,152724,152886,152981,153150,153393,153686,154033,154385,154587,154669,154845,154935,155298,155654,155895,156257,156624,156972,157332,157680,158040,158397,158751,159120,159302,162049,162117,162461,162541,162897,163047,163191,163275,163640,163748,163846,163956,164072,164198,164294,164671,164795,164905,165027,165155,165293,165455,166283,166367,166471,166565,166679,166791,166915,167011,167091,167280,167486,167679,175598,176030,176451,176876,177073,178021,178542,178665,179302,179523,180338,180848,181031,181604,182100,182205,183670,184087,184767,184926,185122,185344,185504,185881,186040,186368,186585,187160,187510,188109,188560,188801,188990,189124,189315,189952,190202,190505",
                        "endLines": "11,12,13,14,17,18,19,20,21,31,33,143,144,145,146,147,148,149,150,151,152,153,154,155,156,157,158,159,160,161,162,163,164,165,170,204,205,206,207,208,209,210,211,212,213,214,238,239,240,241,242,243,244,245,354,355,356,357,358,359,360,361,362,363,364,365,366,367,368,369,370,371,372,373,374,375,376,377,378,379,380,381,382,383,384,385,386,387,388,389,390,391,392,393,394,395,396,397,413,414,415,416,417,418,419,420,421,422,423,424,425,426,427,428,429,430,431,432,433,434,435,436,437,438,439,440,441,442,443,444,445,446,447,448,449,450,451,452,453,454,455,456,457,458,497,498,505,506,513,514,515,523,526,527,530,531,533,534,535,536,537,538,585,586,587,588,625,626,636,645,651,652,653,654,655,675,942,947,948,952,958,962,963,964,975,976,980,986,990,991,1061,1062,1110,1156,1204,1250,1254,1258,2008,2047,2055,2065,2191,2192,2193,2194,2345,2346,2349,2352,2353,2356,2360,2365,2372,2379,2382,2383,2386,2387,2395,2402,2406,2413,2420,2427,2434,2441,2449,2457,2464,2472,2475,2478,2515,2520,2522,2527,2531,2535,2536,2541,2542,2543,2544,2545,2547,2548,2553,2554,2555,2556,2557,2559,2563,2567,2575,2576,2577,2578,2579,2580,2581,2582,2585,2589,2592,2596,2700,2707,2716,2720,2735,2743,2746,2755,2760,2771,2780,2783,2794,2804,2805,2826,2832,2841,2844,2847,2851,2854,2863,2866,2874,2879,2887,2892,2901,2908,2912,2916,2917,2921,2929,2933,2938,2943",
                        "endColumns": "55,59,60,54,52,57,47,57,48,44,52,57,59,57,45,59,52,45,49,46,57,57,58,59,61,61,61,61,61,61,60,61,61,52,61,73,62,67,80,63,65,69,69,69,69,66,62,64,65,52,75,65,86,75,53,78,77,72,64,62,65,70,70,61,68,65,66,66,55,50,52,51,53,70,62,58,61,58,72,66,59,62,74,71,70,55,70,56,56,65,63,70,56,52,62,51,57,66,65,65,80,74,55,70,73,52,60,57,49,48,48,48,51,44,80,53,52,53,50,48,50,60,60,61,49,40,49,47,61,50,48,68,60,55,70,64,62,69,68,69,61,69,69,74,57,61,44,42,46,44,50,47,65,61,62,71,56,56,59,57,69,56,149,130,103,86,156,156,152,80,77,300,165,154,101,10,92,10,106,10,10,10,99,104,10,118,10,10,10,111,120,132,10,10,10,10,10,10,10,10,10,10,72,86,84,98,10,91,10,10,94,10,10,10,10,10,10,81,10,89,10,10,10,10,10,10,10,10,10,10,10,10,10,10,10,10,10,10,10,10,83,10,107,97,109,115,10,95,10,123,109,121,127,10,10,10,83,103,93,113,111,123,95,79,10,10,10,10,10,10,10,10,10,10,10,10,10,10,10,10,10,10,104,10,10,10,10,10,10,10,10,10,10,10,10,10,10,10,10,10,133,10,10,10,10,10",
                        "endOffsets": "553,613,674,729,882,940,988,1046,1095,1542,1640,6792,6852,6910,6956,7016,7069,7115,7165,7212,7270,7328,7387,7447,7509,7571,7633,7695,7757,7819,7880,7942,8004,8057,8336,10882,10945,11013,11094,11158,11224,11294,11364,11434,11504,11571,13044,13109,13175,13228,13304,13370,13457,13533,20989,21068,21146,21219,21284,21347,21413,21484,21555,21617,21686,21752,21819,21886,21942,21993,22046,22098,22152,22223,22286,22345,22407,22466,22539,22606,22666,22729,22804,22876,22947,23003,23074,23131,23188,23254,23318,23389,23446,23499,23562,23614,23672,23739,24975,25041,25122,25197,25253,25324,25398,25451,25512,25570,25620,25669,25718,25767,25819,25864,25945,25999,26052,26106,26157,26206,26257,26318,26379,26441,26491,26532,26582,26630,26692,26743,26792,26861,26922,26978,27049,27114,27177,27247,27316,27386,27448,27518,27588,27663,29927,29989,30320,30363,30693,30738,30789,31170,31362,31424,31604,31676,31801,31858,31918,31976,32046,32103,35393,35524,35628,35715,39396,39553,40582,41071,41400,41701,41867,42022,42124,43550,60928,61271,61378,61607,62016,62248,62348,62453,63051,63170,63405,63820,64058,64170,69394,69527,72799,75970,79239,82407,82631,82868,128642,130301,130751,131466,140564,140651,140736,140835,152454,152546,152719,152881,152976,153145,153388,153681,154028,154380,154582,154664,154840,154930,155293,155649,155890,156252,156619,156967,157327,157675,158035,158392,158746,159115,159297,159460,162112,162456,162536,162892,163042,163186,163270,163635,163743,163841,163951,164067,164193,164289,164666,164790,164900,165022,165150,165288,165450,165606,166362,166466,166560,166674,166786,166910,167006,167086,167275,167481,167674,167884,176025,176446,176871,177068,178016,178537,178660,179297,179518,180333,180843,181026,181599,182095,182200,183665,184082,184762,184921,185117,185339,185499,185876,186035,186363,186580,187155,187505,188104,188555,188796,188985,189119,189310,189947,190197,190500,190715"
                    }
                },
                {
                    "source": "C:\\Users\\Dicky Adhadyanto\\.gradle\\caches\\transforms-2\\files-2.1\\eca1bdbfc7388ebecc8c5db154b2b926\\res\\values\\values.xml",
                    "from": {
                        "startLines": "-1,-1,-1,-1,-1,-1,-1,-1,-1,-1,-1,-1,-1,-1,-1,-1,-1,-1,-1,-1,-1,-1,-1,-1,-1,-1,-1,-1,-1,-1,-1,-1,-1,-1,-1,-1,-1,-1,-1,-1,-1,-1,-1",
                        "startColumns": "-1,-1,-1,-1,-1,-1,-1,-1,-1,-1,-1,-1,-1,-1,-1,-1,-1,-1,-1,-1,-1,-1,-1,-1,-1,-1,-1,-1,-1,-1,-1,-1,-1,-1,-1,-1,-1,-1,-1,-1,-1,-1,-1",
                        "startOffsets": "-1,-1,-1,-1,-1,-1,-1,-1,-1,-1,-1,-1,-1,-1,-1,-1,-1,-1,-1,-1,-1,-1,-1,-1,-1,-1,-1,-1,-1,-1,-1,-1,-1,-1,-1,-1,-1,-1,-1,-1,-1,-1,-1"
                    },
                    "to": {
                        "startLines": "246,247,347,348,349,350,351,352,353,459,460,461,462,463,464,465,466,467,468,469,470,471,472,473,486,487,495,496,508,509,510,511,512,516,539,660,2327,2328,2333,2336,2341,2691,2692",
                        "startColumns": "4,4,4,4,4,4,4,4,4,4,4,4,4,4,4,4,4,4,4,4,4,4,4,4,4,4,4,4,4,4,4,4,4,4,4,4,4,4,4,4,4,4,4",
                        "startOffsets": "13538,13607,20452,20522,20590,20662,20732,20793,20867,27668,27729,27790,27852,27916,27978,28039,28107,28207,28267,28333,28406,28475,28532,28584,29311,29383,29804,29839,30414,30464,30525,30582,30616,30794,32108,42396,151124,151241,151508,151801,152068,175459,175531",
                        "endLines": "246,247,347,348,349,350,351,352,353,459,460,461,462,463,464,465,466,467,468,469,470,471,472,473,486,487,495,496,508,509,510,511,512,516,539,660,2327,2331,2333,2339,2341,2691,2692",
                        "endColumns": "68,62,69,67,71,69,60,73,72,60,60,61,63,61,60,67,99,59,65,72,68,56,51,61,71,75,34,34,49,60,56,33,34,34,69,70,116,12,109,12,128,71,66",
                        "endOffsets": "13602,13665,20517,20585,20657,20727,20788,20862,20935,27724,27785,27847,27911,27973,28034,28102,28202,28262,28328,28401,28470,28527,28579,28641,29378,29454,29834,29869,30459,30520,30577,30611,30646,30824,32173,42462,151236,151437,151613,151997,152192,175526,175593"
                    }
                },
                {
                    "source": "C:\\Users\\Dicky Adhadyanto\\.gradle\\caches\\transforms-2\\files-2.1\\780d21dd828ad32eb7415b54d2dbcfdd\\res\\values\\values.xml",
                    "from": {
                        "startLines": "-1,-1,-1,-1,-1,-1,-1,-1,-1",
                        "startColumns": "-1,-1,-1,-1,-1,-1,-1,-1,-1",
                        "startOffsets": "-1,-1,-1,-1,-1,-1,-1,-1,-1"
                    },
                    "to": {
                        "startLines": "611,612,613,614,615,616,617,618,656",
                        "startColumns": "4,4,4,4,4,4,4,4,4",
                        "startOffsets": "38276,38388,38435,38489,38543,38623,38699,38780,42129",
                        "endColumns": "111,46,53,53,79,75,80,63,73",
                        "endOffsets": "38383,38430,38484,38538,38618,38694,38775,38839,42198"
                    }
                },
                {
                    "source": "C:\\Users\\Dicky Adhadyanto\\.gradle\\caches\\transforms-2\\files-2.1\\12a6b68cda7f874598dd142ab398633a\\res\\values\\values.xml",
                    "from": {
                        "startLines": "-1",
                        "startColumns": "-1",
                        "startOffsets": "-1"
                    },
                    "to": {
                        "startLines": "627",
                        "startColumns": "4",
                        "startOffsets": "39558",
                        "endColumns": "81",
                        "endOffsets": "39635"
                    }
                },
                {
                    "source": "C:\\Users\\Dicky Adhadyanto\\.gradle\\caches\\transforms-2\\files-2.1\\5a12c4e219f356f187cb54ddf17946f7\\res\\values\\values.xml",
                    "from": {
                        "startLines": "-1,-1,-1,-1,-1,-1,-1,-1,-1,-1",
                        "startColumns": "-1,-1,-1,-1,-1,-1,-1,-1,-1,-1",
                        "startOffsets": "-1,-1,-1,-1,-1,-1,-1,-1,-1,-1"
                    },
                    "to": {
                        "startLines": "248,474,475,476,477,2332,2334,2335,2340,2342",
                        "startColumns": "4,4,4,4,4,4,4,4,4,4",
                        "startOffsets": "13670,28646,28699,28752,28805,151442,151618,151740,152002,152197",
                        "endColumns": "88,52,52,52,52,65,121,60,65,66",
                        "endOffsets": "13754,28694,28747,28800,28853,151503,151735,151796,152063,152259"
                    }
                }
            ]
        }
    ]
}